.git_archival.txt
.gitattributes
.gitignore
.gitmodules
CMakeLists.txt
LICENSE
MANIFEST.in
README.md
pyproject.toml
script.sed
setup.py
.github/pull_request_template.md
.github/workflows/cmake_macos.yml
.github/workflows/cmake_ubuntu.yml
.github/workflows/cmake_windows.yml
.github/workflows/publish-to-pypi.yml
.github/workflows/ubuntu_test.yml
.github/workflows/windows_test.yml
benchmarks/CMakeLists.txt
benchmarks/benchmark.cpp
examples/Abstract/Continuous/Network1.JSON
examples/Abstract/Continuous/Network1.cpp
examples/Abstract/Continuous/Network1.py
examples/Abstract/Continuous/Network2.JSON
examples/Abstract/Droplet/Network1.JSON
examples/Abstract/Droplet/Network1.cpp
examples/Abstract/Droplet/Network1.py
examples/Abstract/Droplet/dropletAbstract.JSON
examples/Abstract/Mixing/Case1.JSON
examples/Abstract/Mixing/Case10.JSON
examples/Abstract/Mixing/Case11.JSON
examples/Abstract/Mixing/Case12.JSON
examples/Abstract/Mixing/Case2.JSON
examples/Abstract/Mixing/Case3.JSON
examples/Abstract/Mixing/Case4.JSON
examples/Abstract/Mixing/Case5.JSON
examples/Abstract/Mixing/Case6.JSON
examples/Abstract/Mixing/Case7.JSON
examples/Abstract/Mixing/Case8.JSON
examples/Abstract/Mixing/Case9.JSON
examples/Abstract/Mixing/DiffusionCase1.JSON
examples/Abstract/Mixing/DiffusionCase2.JSON
examples/Abstract/Mixing/DiffusionCase3.JSON
examples/Abstract/Mixing/DiffusionCase4.JSON
examples/Abstract/Mixing/Network1.JSON
examples/Abstract/Mixing/Network2.JSON
examples/Abstract/Mixing/Network3.JSON
examples/Abstract/Mixing/Network4.JSON
examples/Abstract/Mixing/Network5.JSON
examples/Abstract/Mixing/Network6.JSON
examples/CFD/Network1a.JSON
examples/CFD/Network1b.JSON
examples/CFD/Network1c.JSON
examples/CFD/Network1d.JSON
examples/CFD/Network2a.JSON
examples/CFD/Network2b.JSON
examples/CFD/Network2c.JSON
examples/CFD/Network2d.JSON
examples/CFD/Network3a.JSON
examples/CFD/Network3b.JSON
examples/CFD/Network3c.JSON
examples/CFD/Network3d.JSON
examples/CFD/Network4a.JSON
python/mmft.simulator.egg-info/PKG-INFO
python/mmft.simulator.egg-info/SOURCES.txt
python/mmft.simulator.egg-info/dependency_links.txt
python/mmft.simulator.egg-info/top_level.txt
